webpage2pdf/__init__.py
webpage2pdf/webpage2pdf.py
webpage2pdf-1.1.1.dist-info/LICENSE
webpage2pdf-1.1.1.dist-info/METADATA
webpage2pdf-1.1.1.dist-info/WHEEL
webpage2pdf-1.1.1.dist-info/top_level.txt
webpage2pdf-1.1.1.dist-info/RECORD
