Metadata-Version: 2.1
Name: webpage2pdf
Version: 1.1.1
Summary: Html2pdf.Batch processing.
Home-page: https://github.com/czwchenzhun/webpage2pdf
Author: chenzhun
Author-email: 863657500@qq.com
License: UNKNOWN
Platform: UNKNOWN
Classifier: Programming Language :: Python :: 3
Classifier: License :: OSI Approved :: GNU General Public License (GPL)
Classifier: Operating System :: OS Independent
